{
  "material": "Co",
  "book": "Co",
  "page": "Werner-DFT",
  "source": "interpolated_fitting_grid",
  "metadata": {
    "material_query": "Co",
    "shelf": "main",
    "book": "Co",
    "page": "Werner-DFT",
    "path": "database/data/main/Co/nk/Werner-DFT.yml",
    "url": "https://raw.githubusercontent.com/polyanskiy/refractiveindex.info-database/main/database/data/main/Co/nk/Werner-DFT.yml",
    "data_class": "tabulated_nk",
    "k_source": "database",
    "record_wl_min_um": 0.017586,
    "record_wl_max_um": 2.479684,
    "target_wl_min_um": 0.3,
    "target_wl_max_um": 1.1,
    "fit_wl_min_um": 0.3,
    "fit_wl_max_um": 1.1,
    "fit_grid_step_nm": 1.0,
    "fit_grid_npts": 801,
    "raw_points_full": 150,
    "raw_points_overlap": 12,
    "coverage_policy": "overlap_with_target_window",
    "min_raw_overlap_points": 10,
    "reference": "W. S. M. Werner, K. Glantschnig, C. Ambrosch-Draxl.\nOptical constants and inelastic electron-scattering data for 17 elemental metals.\n<a href=\"https://doi.org/10.1063/1.3243762\"><i>J. Phys Chem Ref. Data</i> <b>38</b>, 1013-1092 (2009)</a>\n",
    "comments": "Theoretical density function theory (DFT) calculations.\n",
    "source_window": "interpolated_fitting_grid",
    "fit_grid_points": 801
  },
  "points": {
    "wavelength_um": [
      0.3,
      0.301,
      0.302,
      0.303,
      0.304,
      0.305,
      0.306,
      0.307,
      0.308,
      0.309,
      0.31,
      0.311,
      0.312,
      0.313,
      0.314,
      0.315,
      0.316,
      0.317,
      0.318,
      0.319,
      0.32,
      0.321,
      0.322,
      0.323,
      0.324,
      0.325,
      0.326,
      0.327,
      0.328,
      0.329,
      0.33,
      0.331,
      0.332,
      0.333,
      0.334,
      0.335,
      0.336,
      0.337,
      0.338,
      0.339,
      0.34,
      0.341,
      0.342,
      0.343,
      0.344,
      0.345,
      0.346,
      0.347,
      0.348,
      0.349,
      0.35,
      0.351,
      0.352,
      0.353,
      0.354,
      0.355,
      0.356,
      0.357,
      0.358,
      0.359,
      0.36,
      0.361,
      0.362,
      0.363,
      0.364,
      0.365,
      0.366,
      0.367,
      0.368,
      0.369,
      0.37,
      0.371,
      0.372,
      0.373,
      0.374,
      0.375,
      0.376,
      0.377,
      0.378,
      0.379,
      0.38,
      0.381,
      0.382,
      0.383,
      0.384,
      0.385,
      0.386,
      0.387,
      0.388,
      0.389,
      0.39,
      0.391,
      0.392,
      0.393,
      0.394,
      0.395,
      0.396,
      0.397,
      0.398,
      0.399,
      0.4,
      0.401,
      0.402,
      0.403,
      0.404,
      0.405,
      0.406,
      0.407,
      0.408,
      0.409,
      0.41,
      0.411,
      0.412,
      0.413,
      0.414,
      0.415,
      0.416,
      0.417,
      0.418,
      0.419,
      0.42,
      0.421,
      0.422,
      0.423,
      0.424,
      0.425,
      0.426,
      0.427,
      0.428,
      0.429,
      0.43,
      0.431,
      0.432,
      0.433,
      0.434,
      0.435,
      0.436,
      0.437,
      0.438,
      0.439,
      0.44,
      0.441,
      0.442,
      0.443,
      0.444,
      0.445,
      0.446,
      0.447,
      0.448,
      0.449,
      0.45,
      0.451,
      0.452,
      0.453,
      0.454,
      0.455,
      0.456,
      0.457,
      0.458,
      0.459,
      0.46,
      0.461,
      0.462,
      0.463,
      0.464,
      0.465,
      0.466,
      0.467,
      0.468,
      0.469,
      0.47,
      0.471,
      0.472,
      0.473,
      0.474,
      0.475,
      0.476,
      0.477,
      0.478,
      0.479,
      0.48,
      0.481,
      0.482,
      0.483,
      0.484,
      0.485,
      0.486,
      0.487,
      0.488,
      0.489,
      0.49,
      0.491,
      0.492,
      0.493,
      0.494,
      0.495,
      0.496,
      0.497,
      0.498,
      0.499,
      0.5,
      0.501,
      0.502,
      0.503,
      0.504,
      0.505,
      0.506,
      0.507,
      0.508,
      0.509,
      0.51,
      0.511,
      0.512,
      0.513,
      0.514,
      0.515,
      0.516,
      0.517,
      0.518,
      0.519,
      0.52,
      0.521,
      0.522,
      0.523,
      0.524,
      0.525,
      0.526,
      0.527,
      0.528,
      0.529,
      0.53,
      0.531,
      0.532,
      0.533,
      0.534,
      0.535,
      0.536,
      0.537,
      0.538,
      0.539,
      0.54,
      0.541,
      0.542,
      0.543,
      0.544,
      0.545,
      0.546,
      0.547,
      0.548,
      0.549,
      0.55,
      0.551,
      0.552,
      0.553,
      0.554,
      0.555,
      0.556,
      0.557,
      0.558,
      0.559,
      0.56,
      0.561,
      0.562,
      0.563,
      0.564,
      0.565,
      0.566,
      0.567,
      0.568,
      0.569,
      0.57,
      0.571,
      0.572,
      0.573,
      0.574,
      0.575,
      0.576,
      0.577,
      0.578,
      0.579,
      0.58,
      0.581,
      0.582,
      0.583,
      0.584,
      0.585,
      0.586,
      0.587,
      0.588,
      0.589,
      0.59,
      0.591,
      0.592,
      0.593,
      0.594,
      0.595,
      0.596,
      0.597,
      0.598,
      0.599,
      0.6,
      0.601,
      0.602,
      0.603,
      0.604,
      0.605,
      0.606,
      0.607,
      0.608,
      0.609,
      0.61,
      0.611,
      0.612,
      0.613,
      0.614,
      0.615,
      0.616,
      0.617,
      0.618,
      0.619,
      0.62,
      0.621,
      0.622,
      0.623,
      0.624,
      0.625,
      0.626,
      0.627,
      0.628,
      0.629,
      0.63,
      0.631,
      0.632,
      0.633,
      0.634,
      0.635,
      0.636,
      0.637,
      0.638,
      0.639,
      0.64,
      0.641,
      0.642,
      0.643,
      0.644,
      0.645,
      0.646,
      0.647,
      0.648,
      0.649,
      0.65,
      0.651,
      0.652,
      0.653,
      0.654,
      0.655,
      0.656,
      0.657,
      0.658,
      0.659,
      0.66,
      0.661,
      0.662,
      0.663,
      0.664,
      0.665,
      0.666,
      0.667,
      0.668,
      0.669,
      0.67,
      0.671,
      0.672,
      0.673,
      0.674,
      0.675,
      0.676,
      0.677,
      0.678,
      0.679,
      0.68,
      0.681,
      0.682,
      0.683,
      0.684,
      0.685,
      0.686,
      0.687,
      0.688,
      0.689,
      0.69,
      0.691,
      0.692,
      0.693,
      0.694,
      0.695,
      0.696,
      0.697,
      0.698,
      0.699,
      0.7,
      0.701,
      0.702,
      0.703,
      0.704,
      0.705,
      0.706,
      0.707,
      0.708,
      0.709,
      0.71,
      0.711,
      0.712,
      0.713,
      0.714,
      0.715,
      0.716,
      0.717,
      0.718,
      0.719,
      0.72,
      0.721,
      0.722,
      0.723,
      0.724,
      0.725,
      0.726,
      0.727,
      0.728,
      0.729,
      0.73,
      0.731,
      0.732,
      0.733,
      0.734,
      0.735,
      0.736,
      0.737,
      0.738,
      0.739,
      0.74,
      0.741,
      0.742,
      0.743,
      0.744,
      0.745,
      0.746,
      0.747,
      0.748,
      0.749,
      0.75,
      0.751,
      0.752,
      0.753,
      0.754,
      0.755,
      0.756,
      0.757,
      0.758,
      0.759,
      0.76,
      0.761,
      0.762,
      0.763,
      0.764,
      0.765,
      0.766,
      0.767,
      0.768,
      0.769,
      0.77,
      0.771,
      0.772,
      0.773,
      0.774,
      0.775,
      0.776,
      0.777,
      0.778,
      0.779,
      0.78,
      0.781,
      0.782,
      0.783,
      0.784,
      0.785,
      0.786,
      0.787,
      0.788,
      0.789,
      0.79,
      0.791,
      0.792,
      0.793,
      0.794,
      0.795,
      0.796,
      0.797,
      0.798,
      0.799,
      0.8,
      0.801,
      0.802,
      0.803,
      0.804,
      0.805,
      0.806,
      0.807,
      0.808,
      0.809,
      0.81,
      0.811,
      0.812,
      0.813,
      0.814,
      0.815,
      0.816,
      0.817,
      0.818,
      0.819,
      0.82,
      0.821,
      0.822,
      0.823,
      0.824,
      0.825,
      0.826,
      0.827,
      0.828,
      0.829,
      0.83,
      0.831,
      0.832,
      0.833,
      0.834,
      0.835,
      0.836,
      0.837,
      0.838,
      0.839,
      0.84,
      0.841,
      0.842,
      0.843,
      0.844,
      0.845,
      0.846,
      0.847,
      0.848,
      0.849,
      0.85,
      0.851,
      0.852,
      0.853,
      0.854,
      0.855,
      0.856,
      0.857,
      0.858,
      0.859,
      0.86,
      0.861,
      0.862,
      0.863,
      0.864,
      0.865,
      0.866,
      0.867,
      0.868,
      0.869,
      0.87,
      0.871,
      0.872,
      0.873,
      0.874,
      0.875,
      0.876,
      0.877,
      0.878,
      0.879,
      0.88,
      0.881,
      0.882,
      0.883,
      0.884,
      0.885,
      0.886,
      0.887,
      0.888,
      0.889,
      0.89,
      0.891,
      0.892,
      0.893,
      0.894,
      0.895,
      0.896,
      0.897,
      0.898,
      0.899,
      0.9,
      0.901,
      0.902,
      0.903,
      0.904,
      0.905,
      0.906,
      0.907,
      0.908,
      0.909,
      0.91,
      0.911,
      0.912,
      0.913,
      0.914,
      0.915,
      0.916,
      0.917,
      0.918,
      0.919,
      0.92,
      0.921,
      0.922,
      0.923,
      0.924,
      0.925,
      0.926,
      0.927,
      0.928,
      0.929,
      0.93,
      0.931,
      0.932,
      0.933,
      0.934,
      0.935,
      0.936,
      0.937,
      0.938,
      0.939,
      0.94,
      0.941,
      0.942,
      0.943,
      0.944,
      0.945,
      0.946,
      0.947,
      0.948,
      0.949,
      0.95,
      0.951,
      0.952,
      0.953,
      0.954,
      0.955,
      0.956,
      0.957,
      0.958,
      0.959,
      0.96,
      0.961,
      0.962,
      0.963,
      0.964,
      0.965,
      0.966,
      0.967,
      0.968,
      0.969,
      0.97,
      0.971,
      0.972,
      0.973,
      0.974,
      0.975,
      0.976,
      0.977,
      0.978,
      0.979,
      0.98,
      0.981,
      0.982,
      0.983,
      0.984,
      0.985,
      0.986,
      0.987,
      0.988,
      0.989,
      0.99,
      0.991,
      0.992,
      0.993,
      0.994,
      0.995,
      0.996,
      0.997,
      0.998,
      0.999,
      1.0,
      1.001,
      1.002,
      1.003,
      1.004,
      1.005,
      1.006,
      1.007,
      1.008,
      1.009,
      1.01,
      1.011,
      1.012,
      1.013,
      1.014,
      1.015,
      1.016,
      1.017,
      1.018,
      1.019,
      1.02,
      1.021,
      1.022,
      1.023,
      1.024,
      1.025,
      1.026,
      1.027,
      1.028,
      1.029,
      1.03,
      1.031,
      1.032,
      1.033,
      1.034,
      1.035,
      1.036,
      1.037,
      1.038,
      1.039,
      1.04,
      1.041,
      1.042,
      1.043,
      1.044,
      1.045,
      1.046,
      1.047,
      1.048,
      1.049,
      1.05,
      1.051,
      1.052,
      1.053,
      1.054,
      1.055,
      1.056,
      1.057,
      1.058,
      1.059,
      1.06,
      1.061,
      1.062,
      1.063,
      1.064,
      1.065,
      1.066,
      1.067,
      1.068,
      1.069,
      1.07,
      1.071,
      1.072,
      1.073,
      1.074,
      1.075,
      1.076,
      1.077,
      1.078,
      1.079,
      1.08,
      1.081,
      1.082,
      1.083,
      1.084,
      1.085,
      1.086,
      1.087,
      1.088,
      1.089,
      1.09,
      1.091,
      1.092,
      1.093,
      1.094,
      1.095,
      1.096,
      1.097,
      1.098,
      1.099,
      1.1
    ],
    "n": [
      1.1329439227731462,
      1.1384013602457217,
      1.1438587977182975,
      1.1493162351908732,
      1.1547736726634488,
      1.1602311101360245,
      1.1656885476086003,
      1.1711459850811758,
      1.1766034225537516,
      1.1820608600263274,
      1.1875895717396563,
      1.194828865231067,
      1.2020681587224775,
      1.2093074522138882,
      1.2165467457052987,
      1.2237860391967095,
      1.23102533268812,
      1.2382646261795305,
      1.2455039196709412,
      1.2527432131623517,
      1.2599825066537624,
      1.267221800145173,
      1.2744610936365837,
      1.2817003871279942,
      1.288939680619405,
      1.2961789741108154,
      1.3034182676022261,
      1.3106575610936366,
      1.3178968545850474,
      1.3251361480764579,
      1.3323754415678684,
      1.341389011686992,
      1.3533597095189704,
      1.3653304073509487,
      1.3773011051829271,
      1.3892718030149054,
      1.4012425008468838,
      1.413213198678862,
      1.4251838965108403,
      1.4371545943428188,
      1.449125292174797,
      1.4610959900067755,
      1.4730666878387537,
      1.4850373856707322,
      1.4970080835027098,
      1.5089787813346882,
      1.5209494791666665,
      1.532920176998645,
      1.5448908748306232,
      1.5568615726626016,
      1.5688322704945799,
      1.5808029683265583,
      1.5927736661585365,
      1.6047443639905148,
      1.6167150618224932,
      1.6263017285037984,
      1.6351314103269845,
      1.6439610921501706,
      1.652790773973357,
      1.661620455796543,
      1.6704501376197292,
      1.6792798194429155,
      1.6881095012661016,
      1.6969391830892877,
      1.705768864912474,
      1.7145985467356601,
      1.7234282285588463,
      1.7322579103820324,
      1.7410875922052187,
      1.7499172740284048,
      1.758746955851591,
      1.7675766376747772,
      1.7764063194979633,
      1.7852360013211495,
      1.7940656831443358,
      1.802895364967522,
      1.811725046790708,
      1.8205547286138943,
      1.8293844104370804,
      1.8382140922602666,
      1.8470437740834527,
      1.855873455906639,
      1.8609491742946118,
      1.8624181434997327,
      1.8638871127048537,
      1.8653560819099746,
      1.8668250511150954,
      1.8682940203202165,
      1.8697629895253374,
      1.8712319587304584,
      1.8727009279355793,
      1.8741698971407004,
      1.8756388663458212,
      1.877107835550942,
      1.8785768047560631,
      1.880045773961184,
      1.881514743166305,
      1.882983712371426,
      1.884452681576547,
      1.8859216507816678,
      1.8873906199867887,
      1.8888595891919098,
      1.8903285583970306,
      1.8917975276021517,
      1.8932664968072725,
      1.8947354660123936,
      1.8962044352175145,
      1.8976734044226353,
      1.8991423736277562,
      1.9006113428328772,
      1.902080312037998,
      1.9035492812431192,
      1.90501825044824,
      1.906487219653361,
      1.9090988528386255,
      1.9121570626280908,
      1.915215272417556,
      1.9182734822070213,
      1.9213316919964867,
      1.9243899017859518,
      1.9274481115754172,
      1.9305063213648825,
      1.9335645311543477,
      1.936622740943813,
      1.9396809507332782,
      1.9427391605227435,
      1.945797370312209,
      1.948855580101674,
      1.9519137898911394,
      1.9549719996806048,
      1.95803020947007,
      1.9610884192595353,
      1.9641466290490004,
      1.9672048388384658,
      1.9702630486279311,
      1.9733212584173963,
      1.9763794682068616,
      1.979437677996327,
      1.982495887785792,
      1.9855540975752575,
      1.9886123073647228,
      1.991670517154188,
      1.9947287269436533,
      1.9977869367331185,
      2.000845146522584,
      2.003903356312049,
      2.0069615661015145,
      2.0100197758909797,
      2.013077985680445,
      2.0161361954699104,
      2.0191944052593755,
      2.0225441854275257,
      2.0275724653432405,
      2.0326007452589554,
      2.0376290251746703,
      2.0426573050903847,
      2.0476855850060995,
      2.0527138649218144,
      2.0577421448375293,
      2.0627704247532437,
      2.0677987046689585,
      2.0728269845846734,
      2.0778552645003883,
      2.082883544416103,
      2.0879118243318175,
      2.0929401042475324,
      2.0979683841632473,
      2.102996664078962,
      2.108024943994677,
      2.1130532239103914,
      2.118081503826106,
      2.1231097837418207,
      2.1281380636575356,
      2.1331663435732504,
      2.1381946234889653,
      2.1432229034046797,
      2.1482511833203946,
      2.1532794632361094,
      2.1583077431518243,
      2.163336023067539,
      2.1683643029832536,
      2.1733925828989684,
      2.1784208628146833,
      2.183449142730398,
      2.1884774226461126,
      2.1935057025618274,
      2.1985339824775423,
      2.203562262393257,
      2.208590542308972,
      2.2136188222246864,
      2.2186471021404013,
      2.223675382056116,
      2.228703661971831,
      2.2337319418875454,
      2.2387602218032603,
      2.243788501718975,
      2.2490737042682922,
      2.258180121225319,
      2.2672865381823457,
      2.2763929551393725,
      2.285499372096399,
      2.294605789053426,
      2.3037122060104527,
      2.3128186229674794,
      2.321925039924506,
      2.331031456881533,
      2.3401378738385596,
      2.3492442907955864,
      2.358350707752613,
      2.36745712470964,
      2.3765635416666666,
      2.3856699586236934,
      2.39477637558072,
      2.403882792537747,
      2.4129892094947736,
      2.4220956264518003,
      2.431202043408827,
      2.440308460365854,
      2.4494148773228805,
      2.4585212942799073,
      2.467627711236934,
      2.4767341281939608,
      2.4858405451509875,
      2.4949469621080143,
      2.504053379065041,
      2.5131597960220677,
      2.5222662129790945,
      2.531372629936121,
      2.5404790468931475,
      2.5495854638501747,
      2.558691880807201,
      2.567798297764228,
      2.5769047147212545,
      2.5860111316782812,
      2.595117548635308,
      2.6042239655923347,
      2.6133303825493615,
      2.622436799506388,
      2.631543216463415,
      2.6406496334204417,
      2.6497560503774684,
      2.658862467334495,
      2.667968884291522,
      2.6770753012485486,
      2.6861817182055754,
      2.695288135162602,
      2.704394552119629,
      2.7135009690766556,
      2.7226073860336824,
      2.731713802990709,
      2.740820219947736,
      2.7499266369047626,
      2.7582011686991876,
      2.766440135017422,
      2.7746791013356567,
      2.7829180676538914,
      2.791157033972126,
      2.7993960002903604,
      2.807634966608595,
      2.81587393292683,
      2.8241128992450646,
      2.832351865563299,
      2.8405908318815336,
      2.8488297981997674,
      2.8570687645180017,
      2.8653077308362365,
      2.873546697154471,
      2.881785663472706,
      2.89002462979094,
      2.898263596109175,
      2.9065025624274097,
      2.9147415287456444,
      2.9229804950638787,
      2.9312194613821134,
      2.939458427700348,
      2.9476973940185824,
      2.955936360336817,
      2.964175326655052,
      2.9724142929732866,
      2.980653259291521,
      2.9888922256097556,
      2.9971311919279904,
      3.005370158246225,
      3.0136091245644594,
      3.021848090882694,
      3.030087057200929,
      3.038326023519163,
      3.046564989837398,
      3.0548039561556326,
      3.0630429224738673,
      3.0712818887921016,
      3.0795208551103364,
      3.087759821428571,
      3.095998787746806,
      3.10423775406504,
      3.112476720383275,
      3.1207156867015096,
      3.1289546530197443,
      3.1371936193379786,
      3.1454325856562133,
      3.153671551974448,
      3.1619105182926823,
      3.170149484610917,
      3.178388450929152,
      3.1866274172473865,
      3.194866383565621,
      3.2031053498838555,
      3.2113443162020903,
      3.2195832825203246,
      3.2278222488385593,
      3.236061215156794,
      3.2443001814750287,
      3.2525391477932635,
      3.2607781141114978,
      3.2690170804297325,
      3.2772560467479668,
      3.2854950130662015,
      3.2937339793844362,
      3.301972945702671,
      3.3102119120209057,
      3.318457441282746,
      3.3267794828364945,
      3.3351015243902435,
      3.3434235659439926,
      3.351745607497741,
      3.3600676490514902,
      3.368389690605239,
      3.376711732158988,
      3.385033773712737,
      3.3933558152664856,
      3.4016778568202346,
      3.4099998983739837,
      3.4183219399277323,
      3.4266439814814813,
      3.43496602303523,
      3.443288064588979,
      3.451610106142728,
      3.4599321476964766,
      3.4682541892502257,
      3.4765762308039747,
      3.4848982723577233,
      3.4932203139114724,
      3.501542355465221,
      3.50986439701897,
      3.518186438572719,
      3.5265084801264677,
      3.5348305216802167,
      3.5431525632339658,
      3.5514746047877144,
      3.5597966463414634,
      3.568118687895212,
      3.576440729448961,
      3.58476277100271,
      3.5930848125564587,
      3.601406854110208,
      3.609728895663957,
      3.6180509372177054,
      3.6263729787714545,
      3.634695020325203,
      3.643017061878952,
      3.651339103432701,
      3.65966114498645,
      3.667983186540199,
      3.6763052280939474,
      3.6846272696476965,
      3.6929493112014455,
      3.701271352755194,
      3.709593394308943,
      3.7179154358626922,
      3.726237477416441,
      3.73455951897019,
      3.742881560523939,
      3.7512036020776875,
      3.7595256436314366,
      3.767847685185185,
      3.7761697267389343,
      3.7844917682926833,
      3.792813809846432,
      3.801135851400181,
      3.8094578929539296,
      3.8177799345076786,
      3.8261019760614277,
      3.8344240176151763,
      3.8427460591689253,
      3.8510681007226744,
      3.859390142276423,
      3.867712183830172,
      3.876034225383921,
      3.8843562669376688,
      3.892678308491418,
      3.9010003500451664,
      3.9093223915989155,
      3.917644433152664,
      3.925966474706413,
      3.934288516260162,
      3.942610557813911,
      3.95093259936766,
      3.959254640921409,
      3.9675766824751575,
      3.9758987240289065,
      3.9842207655826556,
      3.992542807136404,
      4.000864848690153,
      4.009186890243902,
      4.017508931797651,
      4.0258309733513995,
      4.034153014905149,
      4.042475056458898,
      4.050797098012646,
      4.055545447154472,
      4.056981761517616,
      4.058418075880759,
      4.059854390243903,
      4.061290704607046,
      4.06272701897019,
      4.064163333333333,
      4.065599647696477,
      4.067035962059621,
      4.0684722764227645,
      4.069908590785908,
      4.071344905149052,
      4.072781219512195,
      4.074217533875339,
      4.075653848238482,
      4.0770901626016265,
      4.07852647696477,
      4.0799627913279135,
      4.081399105691057,
      4.0828354200542005,
      4.084271734417344,
      4.0857080487804875,
      4.087144363143632,
      4.0885806775067755,
      4.090016991869919,
      4.0914533062330625,
      4.092889620596206,
      4.0943259349593495,
      4.095762249322493,
      4.097198563685637,
      4.098634878048781,
      4.100071192411924,
      4.101507506775068,
      4.102943821138211,
      4.104380135501355,
      4.1058164498644985,
      4.107252764227643,
      4.108689078590786,
      4.11012539295393,
      4.111561707317073,
      4.112998021680217,
      4.11443433604336,
      4.115870650406504,
      4.117306964769648,
      4.118743279132792,
      4.120179593495935,
      4.121615907859079,
      4.123052222222222,
      4.124488536585366,
      4.125924850948509,
      4.127361165311653,
      4.128797479674797,
      4.130233794037941,
      4.131670108401084,
      4.133106422764228,
      4.134542737127371,
      4.135979051490515,
      4.137415365853658,
      4.138851680216803,
      4.140287994579946,
      4.14172430894309,
      4.143160623306233,
      4.144596937669377,
      4.14603325203252,
      4.147469566395664,
      4.148905880758808,
      4.150342195121952,
      4.151778509485095,
      4.153214823848239,
      4.154651138211382,
      4.156087452574526,
      4.157523766937669,
      4.158960081300814,
      4.160396395663957,
      4.161832710027101,
      4.163269024390244,
      4.164705338753388,
      4.166141653116531,
      4.167577967479675,
      4.169014281842818,
      4.170450596205963,
      4.171886910569106,
      4.17332322493225,
      4.174759539295393,
      4.176195853658537,
      4.17763216802168,
      4.179068482384824,
      4.180504796747968,
      4.1819411111111116,
      4.183377425474255,
      4.184813739837399,
      4.186250054200542,
      4.187686368563686,
      4.189122682926829,
      4.1905589972899735,
      4.191995311653117,
      4.1934316260162605,
      4.194867940379404,
      4.1963042547425475,
      4.197740569105691,
      4.1991768834688346,
      4.200613197831979,
      4.2020495121951225,
      4.203485826558266,
      4.2049221409214095,
      4.206358455284553,
      4.2077947696476965,
      4.20923108401084,
      4.2106673983739835,
      4.212103712737127,
      4.213540027100271,
      4.214976341463415,
      4.216412655826558,
      4.217848970189702,
      4.2192852845528455,
      4.220721598915989,
      4.2221579132791325,
      4.223594227642277,
      4.226732651394627,
      4.232046208102206,
      4.237359764809785,
      4.242673321517364,
      4.247986878224943,
      4.253300434932522,
      4.258613991640101,
      4.26392754834768,
      4.269241105055259,
      4.274554661762838,
      4.279868218470416,
      4.285181775177996,
      4.290495331885575,
      4.295808888593154,
      4.301122445300733,
      4.3064360020083114,
      4.31174955871589,
      4.317063115423469,
      4.322376672131049,
      4.327690228838628,
      4.3330037855462065,
      4.338317342253785,
      4.343630898961364,
      4.348944455668943,
      4.354258012376522,
      4.3595715690841015,
      4.36488512579168,
      4.370198682499259,
      4.375512239206838,
      4.380825795914417,
      4.386139352621996,
      4.391452909329575,
      4.396766466037154,
      4.402080022744733,
      4.407393579452312,
      4.412707136159891,
      4.4180206928674695,
      4.423334249575048,
      4.428647806282628,
      4.433961362990207,
      4.439274919697786,
      4.4445884764053645,
      4.449902033112943,
      4.455215589820522,
      4.460529146528101,
      4.465842703235681,
      4.4711562599432595,
      4.476469816650838,
      4.481783373358417,
      4.487096930065996,
      4.492410486773575,
      4.4977240434811545,
      4.503037600188733,
      4.508351156896312,
      4.513664713603891,
      4.51897827031147,
      4.524291827019049,
      4.5296053837266275,
      4.534918940434207,
      4.540232497141786,
      4.545546053849365,
      4.550859610556944,
      4.5561731672645225,
      4.561486723972101,
      4.566800280679681,
      4.57211383738726,
      4.577427394094839,
      4.5827409508024175,
      4.588054507509996,
      4.593368064217575,
      4.598681620925154,
      4.603995177632734,
      4.6093087343403125,
      4.614622291047891,
      4.61993584775547,
      4.625249404463049,
      4.630562961170628,
      4.6358765178782075,
      4.641190074585786,
      4.646503631293365,
      4.651817188000944,
      4.657130744708523,
      4.662444301416102,
      4.6677578581236805,
      4.67307141483126,
      4.678384971538839,
      4.683698528246418,
      4.689012084953997,
      4.6943256416615755,
      4.699639198369154,
      4.704952755076733,
      4.710266311784313,
      4.715579868491892,
      4.7208934251994705,
      4.726206981907049,
      4.731520538614628,
      4.736834095322207,
      4.742147652029786,
      4.7474612087373655,
      4.752774765444944,
      4.758088322152523,
      4.763401878860102,
      4.768715435567681,
      4.77402899227526,
      4.779342548982839,
      4.784656105690418,
      4.789969662397997,
      4.795283219105576,
      4.800596775813155,
      4.8059103325207335,
      4.811223889228312,
      4.816537445935891,
      4.82185100264347,
      4.827164559351049,
      4.832478116058628,
      4.837791672766207,
      4.843105229473786,
      4.848418786181365,
      4.853732342888944,
      4.859045899596523,
      4.8643594563041015,
      4.869673013011681,
      4.87498656971926,
      4.880300126426839,
      4.885613683134418,
      4.8909272398419965,
      4.896240796549575,
      4.901554353257154,
      4.906867909964733,
      4.912181466672313,
      4.9174950233798915,
      4.92280858008747,
      4.928122136795049,
      4.933435693502628,
      4.938749250210208,
      4.9440628069177865,
      4.949376363625365,
      4.954689920332944,
      4.960003477040523,
      4.965317033748102,
      4.970630590455681,
      4.9759441471632595,
      4.981257703870839,
      4.986571260578418,
      4.991884817285997,
      4.997198373993576,
      5.0025119307011545,
      5.007825487408733,
      5.013139044116313,
      5.018452600823892,
      5.023766157531471,
      5.0290797142390495,
      5.034393270946628,
      5.039706827654207,
      5.045020384361786,
      5.050333941069366,
      5.0556474977769446,
      5.060961054484523,
      5.066274611192102,
      5.071588167899681,
      5.07690172460726,
      5.08221528131484,
      5.087528838022418,
      5.092842394729997,
      5.098155951437576,
      5.102845528455285,
      5.1032068654019875,
      5.103568202348691,
      5.103929539295393,
      5.1042908762420955,
      5.104652213188799,
      5.105013550135501,
      5.105374887082204,
      5.105736224028907,
      5.10609756097561,
      5.1064588979223124,
      5.106820234869016,
      5.107181571815718,
      5.107542908762421,
      5.107904245709124,
      5.108265582655827,
      5.108626919602529,
      5.108988256549233,
      5.109349593495935,
      5.109710930442638,
      5.110072267389341,
      5.110433604336044,
      5.110794941282746,
      5.1111562782294495,
      5.111517615176152,
      5.111878952122855,
      5.1122402890695575,
      5.11260162601626,
      5.112962962962963,
      5.1133242999096655,
      5.113685636856369,
      5.114046973803071,
      5.114408310749774,
      5.114769647696477,
      5.11513098464318,
      5.115492321589882,
      5.115853658536586,
      5.116214995483288,
      5.116576332429991,
      5.116937669376694,
      5.117299006323397,
      5.117660343270099,
      5.118021680216803,
      5.118383017163505,
      5.118744354110208,
      5.119105691056911,
      5.119467028003614,
      5.119828364950316,
      5.1201897018970195,
      5.120551038843722,
      5.120912375790425,
      5.1212737127371275,
      5.121635049683831,
      5.121996386630533,
      5.122357723577236,
      5.122719060523939,
      5.123080397470641,
      5.123441734417344,
      5.123803071364047,
      5.12416440831075,
      5.124525745257452,
      5.124887082204156,
      5.125248419150858,
      5.125609756097561,
      5.125971093044264,
      5.126332429990967,
      5.126693766937669,
      5.127055103884373,
      5.127416440831075,
      5.127777777777778,
      5.128139114724481,
      5.128500451671184,
      5.128861788617886,
      5.1292231255645895,
      5.129584462511292,
      5.129945799457995,
      5.1303071364046975,
      5.130668473351401,
      5.131029810298103,
      5.1313911472448055,
      5.131752484191509,
      5.132113821138211,
      5.132475158084914,
      5.132836495031617,
      5.13319783197832,
      5.133559168925022,
      5.133920505871726,
      5.134281842818428,
      5.134643179765131,
      5.135004516711834,
      5.135365853658537,
      5.135727190605239,
      5.136088527551943,
      5.136449864498645,
      5.136811201445348,
      5.137172538392051,
      5.137533875338754,
      5.137895212285456,
      5.1382565492321595,
      5.138617886178862,
      5.138979223125565,
      5.1393405600722675,
      5.139701897018971,
      5.140063233965673,
      5.140424570912376,
      5.140785907859079,
      5.141147244805782,
      5.141508581752484,
      5.141869918699187
    ],
    "k": [
      2.7652242650285213,
      2.7803021500658183,
      2.7953800351031153,
      2.8104579201404123,
      2.8255358051777093,
      2.8406136902150063,
      2.8556915752523033,
      2.8707694602896003,
      2.8858473453268974,
      2.9009252303641944,
      2.915951657391725,
      2.9297430921848533,
      2.943534526977982,
      2.9573259617711103,
      2.971117396564239,
      2.9849088313573673,
      2.998700266150496,
      3.0124917009436243,
      3.026283135736753,
      3.0400745705298813,
      3.05386600532301,
      3.0676574401161383,
      3.0814488749092668,
      3.0952403097023953,
      3.1090317444955238,
      3.1228231792886523,
      3.1366146140817808,
      3.1504060488749097,
      3.1641974836680378,
      3.1779889184611667,
      3.1917803532542948,
      3.204074415650407,
      3.2138728573848243,
      3.2236712991192413,
      3.233469740853659,
      3.2432681825880763,
      3.2530666243224937,
      3.2628650660569107,
      3.272663507791328,
      3.2824619495257457,
      3.292260391260163,
      3.30205883299458,
      3.3118572747289976,
      3.321655716463415,
      3.331454158197832,
      3.341252599932249,
      3.3510510416666666,
      3.360849483401084,
      3.3706479251355015,
      3.3804463668699185,
      3.390244808604336,
      3.4000432503387534,
      3.409841692073171,
      3.419640133807588,
      3.4294385755420054,
      3.4339085654519432,
      3.4366866490513415,
      3.4394647326507393,
      3.4422428162501375,
      3.4450208998495357,
      3.447798983448934,
      3.4505770670483322,
      3.45335515064773,
      3.4561332342471283,
      3.4589113178465265,
      3.4616894014459247,
      3.4644674850453225,
      3.4672455686447208,
      3.470023652244119,
      3.4728017358435173,
      3.475579819442915,
      3.4783579030423133,
      3.4811359866417115,
      3.4839140702411098,
      3.486692153840508,
      3.489470237439906,
      3.492248321039304,
      3.4950264046387023,
      3.4978044882381005,
      3.5005825718374983,
      3.5033606554368966,
      3.506138739036295,
      3.5096560819099745,
      3.5138836934981597,
      3.5181113050863453,
      3.5223389166745305,
      3.5265665282627157,
      3.5307941398509013,
      3.5350217514390865,
      3.5392493630272717,
      3.5434769746154573,
      3.5477045862036425,
      3.5519321977918277,
      3.5561598093800133,
      3.5603874209681985,
      3.564615032556384,
      3.5688426441445693,
      3.5730702557327545,
      3.57729786732094,
      3.5815254789091253,
      3.5857530904973105,
      3.589980702085496,
      3.5942083136736813,
      3.5984359252618665,
      3.602663536850052,
      3.6068911484382373,
      3.6111187600264225,
      3.6153463716146077,
      3.6195739832027933,
      3.6238015947909785,
      3.6280292063791637,
      3.6322568179673493,
      3.6364844295555345,
      3.6407120411437197,
      3.647977943094408,
      3.65643127145937,
      3.6648845998243327,
      3.673337928189295,
      3.681791256554257,
      3.6902445849192196,
      3.6986979132841817,
      3.7071512416491443,
      3.7156045700141065,
      3.724057898379069,
      3.7325112267440312,
      3.7409645551089934,
      3.749417883473956,
      3.757871211838918,
      3.7663245402038807,
      3.774777868568843,
      3.7832311969338055,
      3.7916845252987676,
      3.80013785366373,
      3.8085911820286924,
      3.8170445103936546,
      3.825497838758617,
      3.8339511671235793,
      3.842404495488542,
      3.850857823853504,
      3.859311152218466,
      3.867764480583429,
      3.876217808948391,
      3.8846711373133536,
      3.8931244656783157,
      3.9015777940432783,
      3.9100311224082405,
      3.918484450773203,
      3.926937779138165,
      3.9353911075031274,
      3.94384443586809,
      3.952297764233052,
      3.960874789841411,
      3.970163910391483,
      3.979453030941555,
      3.988742151491627,
      3.998031272041699,
      4.0073203925917715,
      4.016609513141844,
      4.025898633691916,
      4.035187754241988,
      4.04447687479206,
      4.053765995342132,
      4.063055115892204,
      4.072344236442276,
      4.081633356992348,
      4.09092247754242,
      4.100211598092493,
      4.109500718642565,
      4.118789839192637,
      4.128078959742708,
      4.13736808029278,
      4.146657200842852,
      4.155946321392924,
      4.165235441942996,
      4.174524562493069,
      4.183813683043141,
      4.193102803593213,
      4.202391924143285,
      4.211681044693357,
      4.220970165243429,
      4.230259285793501,
      4.239548406343573,
      4.248837526893645,
      4.258126647443717,
      4.267415767993789,
      4.276704888543861,
      4.285994009093933,
      4.295283129644006,
      4.304572250194078,
      4.31386137074415,
      4.323150491294222,
      4.332439611844294,
      4.341728732394366,
      4.351017852944438,
      4.36030697349451,
      4.369596094044582,
      4.378779382621952,
      4.386388630589431,
      4.3939978785569105,
      4.40160712652439,
      4.40921637449187,
      4.41682562245935,
      4.424434870426829,
      4.432044118394309,
      4.439653366361789,
      4.447262614329269,
      4.4548718622967485,
      4.4624811102642274,
      4.470090358231707,
      4.477699606199187,
      4.485308854166667,
      4.492918102134147,
      4.500527350101626,
      4.508136598069106,
      4.515745846036586,
      4.523355094004065,
      4.530964341971545,
      4.538573589939024,
      4.546182837906504,
      4.553792085873984,
      4.561401333841464,
      4.569010581808944,
      4.576619829776423,
      4.5842290777439025,
      4.591838325711382,
      4.599447573678862,
      4.607056821646342,
      4.614666069613821,
      4.622275317581301,
      4.629884565548781,
      4.637493813516261,
      4.6451030614837405,
      4.6527123094512195,
      4.660321557418699,
      4.667930805386179,
      4.675540053353659,
      4.683149301321139,
      4.690758549288618,
      4.698367797256098,
      4.705977045223578,
      4.7135862931910575,
      4.721195541158537,
      4.728804789126016,
      4.736414037093496,
      4.744023285060976,
      4.751632533028456,
      4.759241780995936,
      4.766851028963415,
      4.774460276930895,
      4.7820695248983744,
      4.789678772865854,
      4.797288020833334,
      4.801714176829268,
      4.80600424651568,
      4.810294316202091,
      4.814584385888502,
      4.818874455574913,
      4.823164525261324,
      4.827454594947735,
      4.831744664634146,
      4.836034734320558,
      4.840324804006969,
      4.84461487369338,
      4.84890494337979,
      4.853195013066202,
      4.857485082752613,
      4.861775152439024,
      4.866065222125435,
      4.870355291811847,
      4.874645361498257,
      4.878935431184669,
      4.88322550087108,
      4.887515570557491,
      4.891805640243902,
      4.8960957099303135,
      4.900385779616724,
      4.9046758493031355,
      4.908965918989547,
      4.9132559886759575,
      4.917546058362369,
      4.92183612804878,
      4.926126197735191,
      4.930416267421602,
      4.934706337108014,
      4.938996406794424,
      4.943286476480836,
      4.947576546167247,
      4.951866615853658,
      4.956156685540069,
      4.960446755226481,
      4.964736824912892,
      4.969026894599303,
      4.973316964285714,
      4.9776070339721254,
      4.981897103658536,
      4.986187173344947,
      4.990477243031359,
      4.994767312717769,
      4.999057382404181,
      5.003347452090592,
      5.007637521777003,
      5.011927591463414,
      5.016217661149826,
      5.020507730836236,
      5.024797800522648,
      5.029087870209059,
      5.03337793989547,
      5.037668009581881,
      5.0419580792682925,
      5.046248148954703,
      5.0505382186411145,
      5.054828288327526,
      5.0591183580139365,
      5.063408427700348,
      5.067698497386759,
      5.07198856707317,
      5.076278636759581,
      5.080568706445993,
      5.084858776132403,
      5.089148845818815,
      5.092978681120145,
      5.091442999096658,
      5.089907317073171,
      5.0883716350496835,
      5.086835953026196,
      5.08530027100271,
      5.083764588979223,
      5.082228906955736,
      5.080693224932249,
      5.079157542908762,
      5.077621860885276,
      5.076086178861789,
      5.0745504968383015,
      5.073014814814814,
      5.071479132791327,
      5.069943450767841,
      5.068407768744354,
      5.066872086720867,
      5.06533640469738,
      5.063800722673893,
      5.062265040650407,
      5.0607293586269195,
      5.059193676603432,
      5.057657994579945,
      5.056122312556458,
      5.054586630532972,
      5.053050948509485,
      5.051515266485998,
      5.049979584462511,
      5.048443902439024,
      5.0469082204155375,
      5.0453725383920505,
      5.043836856368563,
      5.042301174345076,
      5.040765492321589,
      5.039229810298103,
      5.037694128274616,
      5.036158446251129,
      5.034622764227642,
      5.033087082204155,
      5.0315514001806685,
      5.030015718157181,
      5.028480036133694,
      5.026944354110207,
      5.02540867208672,
      5.023872990063234,
      5.022337308039747,
      5.02080162601626,
      5.019265943992773,
      5.017730261969286,
      5.016194579945799,
      5.014658897922312,
      5.013123215898825,
      5.011587533875338,
      5.010051851851851,
      5.008516169828365,
      5.006980487804878,
      5.005444805781391,
      5.003909123757904,
      5.002373441734417,
      5.00083775971093,
      4.999302077687443,
      4.997766395663956,
      4.996230713640469,
      4.994695031616983,
      4.993159349593496,
      4.991623667570009,
      4.990087985546522,
      4.988552303523035,
      4.987016621499548,
      4.985480939476061,
      4.983945257452574,
      4.982409575429087,
      4.980873893405601,
      4.979338211382114,
      4.977802529358627,
      4.97626684733514,
      4.974731165311653,
      4.973195483288166,
      4.971659801264679,
      4.970124119241192,
      4.968588437217705,
      4.967052755194218,
      4.965517073170732,
      4.963981391147245,
      4.962445709123758,
      4.960910027100271,
      4.9593743450767835,
      4.957838663053297,
      4.957757540650406,
      4.959024478319782,
      4.960291415989159,
      4.961558353658536,
      4.9628252913279125,
      4.9640922289972895,
      4.9653591666666665,
      4.966626104336043,
      4.96789304200542,
      4.969159979674797,
      4.970426917344173,
      4.97169385501355,
      4.972960792682926,
      4.974227730352303,
      4.97549466802168,
      4.976761605691056,
      4.978028543360433,
      4.97929548102981,
      4.980562418699186,
      4.981829356368563,
      4.98309629403794,
      4.9843632317073165,
      4.985630169376694,
      4.98689710704607,
      4.988164044715447,
      4.989430982384824,
      4.9906979200542,
      4.991964857723577,
      4.993231795392954,
      4.99449873306233,
      4.995765670731707,
      4.997032608401084,
      4.99829954607046,
      4.999566483739837,
      5.000833421409213,
      5.00210035907859,
      5.003367296747967,
      5.004634234417344,
      5.005901172086721,
      5.007168109756098,
      5.008435047425474,
      5.009701985094851,
      5.010968922764228,
      5.012235860433604,
      5.013502798102981,
      5.014769735772357,
      5.016036673441734,
      5.017303611111111,
      5.018570548780487,
      5.019837486449864,
      5.021104424119241,
      5.022371361788617,
      5.0236382994579944,
      5.0249052371273715,
      5.026172174796748,
      5.027439112466125,
      5.028706050135501,
      5.029972987804878,
      5.031239925474255,
      5.032506863143631,
      5.033773800813008,
      5.035040738482385,
      5.036307676151761,
      5.037574613821138,
      5.038841551490515,
      5.040108489159891,
      5.041375426829268,
      5.0426423644986444,
      5.0439093021680215,
      5.0451762398373985,
      5.046443177506775,
      5.047710115176152,
      5.048977052845529,
      5.050243990514905,
      5.051510928184282,
      5.052777865853659,
      5.054044803523035,
      5.055311741192412,
      5.056578678861788,
      5.057845616531165,
      5.059112554200542,
      5.060379491869918,
      5.061646429539295,
      5.062913367208672,
      5.0641803048780485,
      5.0654472425474255,
      5.0667141802168025,
      5.067981117886179,
      5.069248055555556,
      5.070514993224932,
      5.071781930894309,
      5.073048868563686,
      5.074315806233062,
      5.075582743902439,
      5.076849681571816,
      5.078116619241192,
      5.079383556910569,
      5.080650494579946,
      5.081917432249322,
      5.083184369918699,
      5.0844513075880755,
      5.0857182452574525,
      5.0869851829268296,
      5.088252120596206,
      5.089519058265583,
      5.090785995934959,
      5.092052933604336,
      5.093319871273713,
      5.094586808943089,
      5.095853746612466,
      5.097120684281843,
      5.098387621951219,
      5.099654559620596,
      5.100921497289973,
      5.102188434959349,
      5.103455372628726,
      5.1047223102981025,
      5.1059892479674795,
      5.107430015788232,
      5.109092921911767,
      5.110755828035303,
      5.112418734158838,
      5.114081640282373,
      5.115744546405908,
      5.117407452529444,
      5.119070358652979,
      5.120733264776515,
      5.12239617090005,
      5.124059077023586,
      5.125721983147121,
      5.127384889270656,
      5.129047795394191,
      5.130710701517727,
      5.132373607641262,
      5.134036513764798,
      5.135699419888333,
      5.137362326011869,
      5.1390252321354035,
      5.140688138258939,
      5.142351044382474,
      5.14401395050601,
      5.145676856629545,
      5.147339762753081,
      5.149002668876616,
      5.1506655750001515,
      5.1523284811236865,
      5.153991387247222,
      5.155654293370757,
      5.157317199494293,
      5.158980105617828,
      5.160643011741363,
      5.162305917864899,
      5.163968823988434,
      5.165631730111969,
      5.167294636235504,
      5.16895754235904,
      5.170620448482575,
      5.172283354606111,
      5.173946260729646,
      5.175609166853182,
      5.1772720729767165,
      5.178934979100252,
      5.180597885223787,
      5.182260791347323,
      5.183923697470858,
      5.185586603594394,
      5.187249509717929,
      5.188912415841465,
      5.1905753219649995,
      5.192238228088535,
      5.19390113421207,
      5.195564040335606,
      5.197226946459141,
      5.198889852582677,
      5.200552758706212,
      5.2022156648297475,
      5.203878570953282,
      5.205541477076818,
      5.207204383200353,
      5.208867289323889,
      5.210530195447424,
      5.212193101570959,
      5.213856007694495,
      5.21551891381803,
      5.217181819941565,
      5.2188447260651,
      5.220507632188636,
      5.222170538312171,
      5.223833444435707,
      5.225496350559242,
      5.227159256682778,
      5.2288221628063125,
      5.230485068929848,
      5.232147975053383,
      5.233810881176919,
      5.235473787300454,
      5.23713669342399,
      5.238799599547525,
      5.2404625056710605,
      5.2421254117945955,
      5.243788317918131,
      5.245451224041666,
      5.247114130165202,
      5.248777036288737,
      5.250439942412273,
      5.252102848535808,
      5.2537657546593435,
      5.255428660782878,
      5.257091566906414,
      5.258754473029949,
      5.260417379153484,
      5.26208028527702,
      5.263743191400555,
      5.265406097524091,
      5.2670690036476255,
      5.268731909771161,
      5.270394815894696,
      5.272057722018232,
      5.273720628141767,
      5.275383534265303,
      5.277046440388838,
      5.278709346512374,
      5.2803722526359085,
      5.282035158759444,
      5.283698064882979,
      5.285360971006515,
      5.28702387713005,
      5.288686783253586,
      5.290349689377121,
      5.292012595500656,
      5.293675501624191,
      5.295338407747726,
      5.297001313871262,
      5.298664219994797,
      5.300327126118333,
      5.301990032241868,
      5.303652938365404,
      5.305315844488939,
      5.306978750612474,
      5.308641656736009,
      5.310304562859545,
      5.31196746898308,
      5.313630375106616,
      5.315293281230151,
      5.316956187353687,
      5.3186190934772215,
      5.320281999600757,
      5.321944905724292,
      5.323607811847828,
      5.325270717971363,
      5.326933624094899,
      5.328596530218434,
      5.3302594363419695,
      5.3319223424655044,
      5.33358524858904,
      5.335248154712575,
      5.336911060836111,
      5.338573966959646,
      5.340236873083181,
      5.341899779206717,
      5.343562685330252,
      5.345225591453787,
      5.346888497577322,
      5.348551403700858,
      5.350214309824393,
      5.351877215947929,
      5.353540122071464,
      5.355203028195,
      5.3568659343185345,
      5.35852884044207,
      5.360191746565605,
      5.361854652689141,
      5.363517558812676,
      5.365180464936212,
      5.366843371059747,
      5.3685062771832825,
      5.3701691833068175,
      5.371832089430353,
      5.373494995553888,
      5.375157901677424,
      5.376820807800959,
      5.378483713924495,
      5.38014662004803,
      5.381109146341463,
      5.377213482384824,
      5.373317818428184,
      5.369422154471545,
      5.365526490514905,
      5.361630826558265,
      5.357735162601626,
      5.353839498644986,
      5.3499438346883466,
      5.346048170731708,
      5.342152506775068,
      5.338256842818429,
      5.334361178861789,
      5.330465514905149,
      5.326569850948509,
      5.32267418699187,
      5.31877852303523,
      5.314882859078591,
      5.310987195121951,
      5.307091531165312,
      5.303195867208672,
      5.299300203252033,
      5.295404539295393,
      5.291508875338754,
      5.287613211382114,
      5.283717547425475,
      5.279821883468834,
      5.275926219512195,
      5.272030555555555,
      5.268134891598916,
      5.2642392276422765,
      5.2603435636856375,
      5.256447899728997,
      5.252552235772358,
      5.248656571815718,
      5.244760907859079,
      5.240865243902439,
      5.2369695799458,
      5.23307391598916,
      5.22917825203252,
      5.22528258807588,
      5.221386924119241,
      5.217491260162602,
      5.213595596205963,
      5.209699932249323,
      5.205804268292683,
      5.201908604336043,
      5.198012940379404,
      5.194117276422764,
      5.190221612466125,
      5.186325948509485,
      5.182430284552846,
      5.1785346205962055,
      5.1746389566395665,
      5.170743292682927,
      5.166847628726288,
      5.162951964769648,
      5.159056300813009,
      5.155160636856368,
      5.151264972899729,
      5.147369308943089,
      5.14347364498645,
      5.13957798102981,
      5.135682317073171,
      5.1317866531165315,
      5.127890989159892,
      5.123995325203252,
      5.120099661246613,
      5.116203997289973,
      5.112308333333334,
      5.108412669376694,
      5.104517005420054,
      5.100621341463414,
      5.096725677506775,
      5.092830013550135,
      5.088934349593496,
      5.085038685636857,
      5.081143021680218,
      5.077247357723577,
      5.073351693766938,
      5.069456029810298,
      5.065560365853659,
      5.061664701897019,
      5.05776903794038,
      5.053873373983739,
      5.0499777100271,
      5.0460820460704605,
      5.0421863821138215,
      5.038290718157182,
      5.034395054200543,
      5.030499390243902,
      5.026603726287263,
      5.022708062330623,
      5.018812398373984,
      5.014916734417344,
      5.011021070460705,
      5.007125406504065,
      5.0032297425474255,
      4.999334078590786,
      4.995438414634147,
      4.991542750677507,
      4.987647086720868,
      4.983751422764228,
      4.979855758807588,
      4.975960094850948,
      4.972064430894309,
      4.968168766937669,
      4.96427310298103,
      4.96037743902439
    ],
    "eps_real": [
      -6.362903303753921,
      -6.434122388651303,
      -6.505736591535546,
      -6.57774591240665,
      -6.650150351264616,
      -6.7229499081094435,
      -6.796144582941133,
      -6.869734375759686,
      -6.9437192865650985,
      -7.018099315357373,
      -7.092405077340766,
      -7.1557785690155065,
      -7.2194276532970445,
      -7.2833523301853775,
      -7.347552599680507,
      -7.412028461782434,
      -7.476779916491158,
      -7.541806963806677,
      -7.607109603728994,
      -7.672687836258108,
      -7.738541661394018,
      -7.804671079136726,
      -7.871076089486229,
      -7.937756692442529,
      -8.004712888005626,
      -8.071944676175521,
      -8.13945205695221,
      -8.207235030335701,
      -8.27529359632598,
      -8.343627754923064,
      -8.412237506126939,
      -8.466768380350892,
      -8.497396240085623,
      -8.52792952352803,
      -8.558368230678115,
      -8.588712361535878,
      -8.618961916101314,
      -8.649116894374428,
      -8.679177296355219,
      -8.709143122043688,
      -8.739014371439831,
      -8.768791044543649,
      -8.798473141355146,
      -8.828060661874321,
      -8.85755360610117,
      -8.886951974035693,
      -8.916255765677898,
      -8.945464981027776,
      -8.974579620085333,
      -9.003599682850563,
      -9.032525169323472,
      -9.061356079504058,
      -9.09009241339232,
      -9.118734170988256,
      -9.147281352291872,
      -9.14687072374978,
      -9.137160394729825,
      -9.12730957464464,
      -9.11731826349423,
      -9.107186461278593,
      -9.096914167997731,
      -9.086501383651639,
      -9.07594810824032,
      -9.065254341763776,
      -9.054420084222006,
      -9.043445335615006,
      -9.032330095942779,
      -9.021074365205328,
      -9.009678143402649,
      -8.998141430534742,
      -8.986464226601608,
      -8.974646531603248,
      -8.962688345539663,
      -8.95058966841085,
      -8.938350500216808,
      -8.925970840957538,
      -8.913450690633045,
      -8.900790049243325,
      -8.887988916788377,
      -8.875047293268198,
      -8.861965178682796,
      -8.848742573032167,
      -8.854553983979875,
      -8.878777270195279,
      -8.903031986069111,
      -8.927318131601373,
      -8.951635706792064,
      -8.975984711641189,
      -9.00036514614874,
      -9.024777010314722,
      -9.049220304139135,
      -9.073695027621975,
      -9.098201180763246,
      -9.12273876356295,
      -9.14730777602108,
      -9.171908218137643,
      -9.196540089912634,
      -9.221203391346055,
      -9.245898122437907,
      -9.270624283188187,
      -9.295381873596899,
      -9.320170893664042,
      -9.34499134338961,
      -9.36984322277361,
      -9.394726531816044,
      -9.419641270516905,
      -9.444587438876194,
      -9.469565036893913,
      -9.494574064570067,
      -9.519614521904646,
      -9.544686408897658,
      -9.569789725549098,
      -9.594924471858967,
      -9.620090647827267,
      -9.663084643393551,
      -9.713145010747498,
      -9.763329590328105,
      -9.81363838213537,
      -9.864071386169291,
      -9.914628602429879,
      -9.965310030917118,
      -10.016115671631022,
      -10.067045524571581,
      -10.118099589738803,
      -10.16927786713268,
      -10.220580356753215,
      -10.272007058600412,
      -10.323557972674267,
      -10.375233098974784,
      -10.427032437501955,
      -10.47895598825579,
      -10.531003751236279,
      -10.583175726443427,
      -10.63547191387724,
      -10.687892313537704,
      -10.740436925424834,
      -10.793105749538618,
      -10.845898785879065,
      -10.898816034446169,
      -10.95185749523993,
      -11.005023168260355,
      -11.058313053507433,
      -11.111727150981174,
      -11.165265460681574,
      -11.218927982608633,
      -11.27271471676235,
      -11.326625663142728,
      -11.38066082174976,
      -11.434820192583453,
      -11.489103775643807,
      -11.543511570930818,
      -11.597844118794548,
      -11.651151373156926,
      -11.704580635842667,
      -11.758131906851776,
      -11.811805186184253,
      -11.865600473840097,
      -11.919517769819306,
      -11.973557074121876,
      -12.02771838674782,
      -12.082001707697124,
      -12.136407036969793,
      -12.19093437456583,
      -12.245583720485232,
      -12.300355074728003,
      -12.35524843729414,
      -12.410263808183647,
      -12.465401187396512,
      -12.520660574932746,
      -12.576041970792337,
      -12.631545374975305,
      -12.687170787481637,
      -12.74291820831133,
      -12.798787637464393,
      -12.85477907494083,
      -12.910892520740628,
      -12.967127974863788,
      -13.023485437310313,
      -13.079964908080205,
      -13.136566387173465,
      -13.193289874590093,
      -13.25013537033008,
      -13.307102874393438,
      -13.36419238678016,
      -13.421403907490252,
      -13.478737436523705,
      -13.536192973880524,
      -13.593770519560717,
      -13.651470073564273,
      -13.70929163589119,
      -13.767235206541477,
      -13.825300785515125,
      -13.883488372812142,
      -13.941797968432526,
      -14.000229572376272,
      -14.058783184643385,
      -14.115376354443981,
      -14.141027758667024,
      -14.166629110539747,
      -14.192180410062134,
      -14.217681657234195,
      -14.24313285205593,
      -14.268533994527326,
      -14.2938850846484,
      -14.319186122419143,
      -14.344437107839559,
      -14.369638040909644,
      -14.394788921629395,
      -14.419889749998823,
      -14.44494052601792,
      -14.46994124968669,
      -14.494891921005129,
      -14.519792539973231,
      -14.544643106591014,
      -14.569443620858467,
      -14.594194082775587,
      -14.618894492342381,
      -14.643544849558838,
      -14.668145154424975,
      -14.69269540694078,
      -14.717195607106257,
      -14.741645754921405,
      -14.766045850386213,
      -14.790395893500703,
      -14.81469588426486,
      -14.83894582267869,
      -14.863145708742193,
      -14.887295542455355,
      -14.9113953238182,
      -14.935445052830714,
      -14.9594447294929,
      -14.983394353804751,
      -15.00729392576627,
      -15.031143445377467,
      -15.054942912638333,
      -15.078692327548872,
      -15.10239169010908,
      -15.126041000318951,
      -15.149640258178499,
      -15.17318946368772,
      -15.196688616846613,
      -15.220137717655176,
      -15.243536766113397,
      -15.266885762221303,
      -15.290184705978879,
      -15.313433597386123,
      -15.336632436443036,
      -15.359781223149616,
      -15.382879957505873,
      -15.405928639511803,
      -15.428927269167401,
      -15.45187584647267,
      -15.448785348949611,
      -15.444485796891534,
      -15.440087293097296,
      -15.435589837566893,
      -15.430993430300338,
      -15.426298071297632,
      -15.421503760558755,
      -15.416610498083726,
      -15.411618283872546,
      -15.406527117925208,
      -15.4013370002417,
      -15.396047930822041,
      -15.39065990966623,
      -15.38517293677426,
      -15.379587012146123,
      -15.373902135781837,
      -15.368118307681396,
      -15.362235527844787,
      -15.356253796272032,
      -15.350173112963114,
      -15.343993477918035,
      -15.337714891136805,
      -15.331337352619416,
      -15.324860862365867,
      -15.318285420376162,
      -15.311611026650302,
      -15.304837681188278,
      -15.297965383990105,
      -15.290994135055772,
      -15.283923934385275,
      -15.276754781978623,
      -15.269486677835822,
      -15.262119621956852,
      -15.25465361434173,
      -15.247088654990455,
      -15.239424743903013,
      -15.23166188107942,
      -15.22380006651967,
      -15.215839300223767,
      -15.20777958219169,
      -15.19962091242347,
      -15.191363290919089,
      -15.183006717678545,
      -15.174551192701852,
      -15.165996715988996,
      -15.157343287539979,
      -15.148590907354814,
      -15.13973957543349,
      -15.130789291775999,
      -15.121740056382361,
      -15.112591869252565,
      -15.1033447303866,
      -15.09399863978449,
      -15.084553597446224,
      -15.075009603371786,
      -15.065366657561201,
      -15.055624760014464,
      -15.045783910731553,
      -15.035844109712496,
      -15.025805356957283,
      -15.0156676524659,
      -15.005430996238374,
      -14.995095388274688,
      -14.984660828574835,
      -14.974127317138834,
      -14.963494853966674,
      -14.952763439058348,
      -14.941933072413875,
      -14.926272056739462,
      -14.855330085628513,
      -14.784254318404875,
      -14.713044755068548,
      -14.64170139561953,
      -14.570224240057827,
      -14.498613288383433,
      -14.426868540596343,
      -14.354989996696565,
      -14.282977656684098,
      -14.210831520558944,
      -14.138551588321095,
      -14.066137859970558,
      -13.993590335507328,
      -13.920909014931409,
      -13.84809389824281,
      -13.775144985441509,
      -13.70206227652752,
      -13.628845771500837,
      -13.555495470361466,
      -13.482011373109419,
      -13.408393479744666,
      -13.334641790267229,
      -13.260756304677097,
      -13.186737022974274,
      -13.112583945158773,
      -13.038297071230572,
      -12.96387640118968,
      -12.889321935036103,
      -12.814633672769832,
      -12.739811614390879,
      -12.664855759899226,
      -12.589766109294883,
      -12.514542662577854,
      -12.43918541974813,
      -12.363694380805727,
      -12.288069545750627,
      -12.212310914582833,
      -12.136418487302352,
      -12.060392263909177,
      -11.984232244403325,
      -11.907938428784773,
      -11.831510817053527,
      -11.754949409209598,
      -11.678254205252973,
      -11.601425205183668,
      -11.524462409001668,
      -11.44736581670697,
      -11.370135428299589,
      -11.292771243779514,
      -11.215273263146758,
      -11.137641486401302,
      -11.059875913543163,
      -10.981976544572325,
      -10.903943379488803,
      -10.825776418292598,
      -10.74747566098369,
      -10.669041107562098,
      -10.590472758027813,
      -10.511770612380838,
      -10.432934670621181,
      -10.353964932748825,
      -10.27486139876378,
      -10.195624068666046,
      -10.116252942455628,
      -10.036748020132514,
      -9.957109301696708,
      -9.87733678714821,
      -9.797430476487033,
      -9.717390369713165,
      -9.6372164668266,
      -9.556908767827343,
      -9.476467272715398,
      -9.395891981490768,
      -9.31518289415344,
      -9.234340010703425,
      -9.153363331140719,
      -9.072252855465319,
      -8.99100858367724,
      -8.909630515776463,
      -8.828118651762995,
      -8.746472991636839,
      -8.664693535397992,
      -8.58278028304646,
      -8.500733234582233,
      -8.418552390005317,
      -8.336237749315703,
      -8.253789312513407,
      -8.171207079598432,
      -8.1319109579406,
      -8.132822763288212,
      -8.133733652900057,
      -8.134643626776116,
      -8.135552684916382,
      -8.136460827320876,
      -8.137368053989583,
      -8.1382743649225,
      -8.139179760119635,
      -8.140084239580993,
      -8.140987803306562,
      -8.141890451296353,
      -8.142792183550354,
      -8.143693000068579,
      -8.14459290085102,
      -8.145491885897663,
      -8.146389955208537,
      -8.147287108783631,
      -8.148183346622929,
      -8.149078668726453,
      -8.149973075094197,
      -8.150866565726144,
      -8.151759140622314,
      -8.152650799782696,
      -8.153541543207304,
      -8.15443137089613,
      -8.155320282849162,
      -8.15620827906642,
      -8.157095359547895,
      -8.157981524293572,
      -8.158866773303478,
      -8.159751106577604,
      -8.160634524115936,
      -8.161517025918492,
      -8.16239861198526,
      -8.16327928231625,
      -8.164159036911451,
      -8.165037875770864,
      -8.165915798894508,
      -8.166792806282364,
      -8.167668897934432,
      -8.16854407385072,
      -8.169418334031228,
      -8.170291678475936,
      -8.171164107184877,
      -8.172035620158026,
      -8.172906217395399,
      -8.173775898896988,
      -8.174644664662788,
      -8.175512514692812,
      -8.176379448987053,
      -8.177245467545493,
      -8.178110570368167,
      -8.178974757455057,
      -8.179838028806154,
      -8.180700384421478,
      -8.18156182430101,
      -8.182422348444767,
      -8.183281956852733,
      -8.184140649524913,
      -8.18499842646132,
      -8.185855287661946,
      -8.186711233126777,
      -8.187566262855833,
      -8.188420376849107,
      -8.18927357510658,
      -8.190125857628285,
      -8.1909772244142,
      -8.191827675464342,
      -8.192677210778697,
      -8.19352583035726,
      -8.194373534200054,
      -8.19522032230705,
      -8.196066194678266,
      -8.196911151313705,
      -8.19775519221336,
      -8.198598317377224,
      -8.199440526805313,
      -8.20028182049761,
      -8.201122198454131,
      -8.201961660674865,
      -8.202800207159813,
      -8.203637837908984,
      -8.204474552922374,
      -8.205310352199971,
      -8.206145235741792,
      -8.206979203547832,
      -8.207812255618071,
      -8.208644391952545,
      -8.209475612551223,
      -8.21030591741413,
      -8.211135306541253,
      -8.211963779932583,
      -8.212791337588136,
      -8.213617979507902,
      -8.214443705691881,
      -8.215268516140087,
      -8.216092410852509,
      -8.216915389829138,
      -8.217737453069994,
      -8.218558600575056,
      -8.219378832344338,
      -8.220198148377843,
      -8.221016548675555,
      -8.221834033237494,
      -8.222650602063641,
      -8.22346625515401,
      -8.224280992508598,
      -8.225094814127395,
      -8.225907720010417,
      -8.226719710157647,
      -8.227530784569092,
      -8.228340943244765,
      -8.229150186184654,
      -8.22995851338875,
      -8.23076592485707,
      -8.231572420589599,
      -8.232378000586348,
      -8.220572459809125,
      -8.192615377216654,
      -8.164607357367977,
      -8.136548400263074,
      -8.108438505901958,
      -8.080277674284607,
      -8.05206590541106,
      -8.023803199281286,
      -7.995489555895298,
      -7.9671249752530855,
      -7.9387094573546655,
      -7.910243002200009,
      -7.881725609789153,
      -7.853157280122067,
      -7.824538013198775,
      -7.795867809019254,
      -7.767146667583524,
      -7.73837458889157,
      -7.709551572943397,
      -7.680677619739006,
      -7.651752729278404,
      -7.6227769015615765,
      -7.593750136588539,
      -7.5646724343592755,
      -7.535543794873804,
      -7.506364218132096,
      -7.4771337041341885,
      -7.447852252880052,
      -7.418519864369709,
      -7.38913653860314,
      -7.359702275580359,
      -7.330217075301342,
      -7.300680937766119,
      -7.271093862974684,
      -7.241455850927024,
      -7.2117669016231565,
      -7.18202701506306,
      -7.152236191246752,
      -7.122394430174212,
      -7.092501731845471,
      -7.062558096260502,
      -7.032563523419325,
      -7.002518013321923,
      -6.97242156596831,
      -6.942274181358468,
      -6.91207585949241,
      -6.881826600370136,
      -6.85152640399165,
      -6.821175270356939,
      -6.790773199466019,
      -6.760320191318872,
      -6.729816245915505,
      -6.699261363255921,
      -6.6686555433401296,
      -6.63799878616811,
      -6.6072910917398815,
      -6.576532460055429,
      -6.545722891114764,
      -6.514862384917863,
      -6.483950941464766,
      -6.452988560755436,
      -6.421975242789903,
      -6.390910987568141,
      -6.35979579509016,
      -6.32862966535596,
      -6.297412598365543,
      -6.266144594118919,
      -6.234825652616066,
      -6.203455773857005,
      -6.172034957841715,
      -6.140563204570218,
      -6.109040514042487,
      -6.077466886258554,
      -6.0458423212183945,
      -6.014166818922025,
      -5.98244037936943,
      -5.950663002560623,
      -5.918834688495584,
      -5.886955437174344,
      -5.855025248596876,
      -5.8230441227632,
      -5.791012059673296,
      -5.758929059327184,
      -5.726795121724843,
      -5.69461024686629,
      -5.662374434751513,
      -5.630087685380528,
      -5.597749998753318,
      -5.565361374869897,
      -5.53292181373025,
      -5.500431315334397,
      -5.467889879682305,
      -5.435297506774004,
      -5.402654196609492,
      -5.369959949188758,
      -5.337214764511813,
      -5.30441864257864,
      -5.2715715833892585,
      -5.23867358694364,
      -5.205724653241826,
      -5.17272478228378,
      -5.139673974069529,
      -5.106572228599046,
      -5.073419545872359,
      -5.040215925889435,
      -5.006961368650308,
      -4.973655874154956,
      -4.940299442403396,
      -4.906892073395608,
      -4.873433767131612,
      -4.839924523611391,
      -4.806364342834947,
      -4.772753224802297,
      -4.739091169513421,
      -4.705378176968334,
      -4.671614247167013,
      -4.63779938010949,
      -4.603933575795741,
      -4.570016834225785,
      -4.5360491553996,
      -4.502030539317204,
      -4.467960985978578,
      -4.433840495383748,
      -4.399669067532691,
      -4.365446702425425,
      -4.331173400061931,
      -4.296849160442229,
      -4.262473983566302,
      -4.228047869434164,
      -4.193570818045792,
      -4.159042829401221,
      -4.124463903500422,
      -4.08983404034341,
      -4.055153239930174,
      -4.020421502260722,
      -3.985638827335049,
      -3.9508052151531694,
      -3.9159206657150603,
      -3.880985179020744,
      -3.845998755070202,
      -3.8109613938634386,
      -3.7758730954004713,
      -3.7407338596812623,
      -3.7055436867058584,
      -3.6703025764742256,
      -3.635010528986382,
      -3.5996675442423127,
      -3.564273622242036,
      -3.5288287629855217,
      -3.493332966472809,
      -3.457786232703867,
      -3.4221885616787175,
      -3.386539953397343,
      -3.3508404078597573,
      -3.3150899250659425,
      -3.279288505015915,
      -3.2434361477096676,
      -3.207532853147209,
      -3.171578621328525,
      -3.13557345225363,
      -3.09951734592251,
      -3.063410302335173,
      -3.0272523214916167,
      -2.9910434033918523,
      -2.954783548035863,
      -2.9173031575636488,
      -2.871704524055147,
      -2.826135981813172,
      -2.7805975308377624,
      -2.735089171128896,
      -2.6896109026865664,
      -2.6441627255108022,
      -2.5987446396015685,
      -2.55335664495889,
      -2.5079987415827625,
      -2.462670929473183,
      -2.417373208630148,
      -2.3721055790536645,
      -2.326868040743718,
      -2.2816605937003303,
      -2.2364832379234905,
      -2.1913359734131985,
      -2.146218800169454,
      -2.101131718192258,
      -2.05607472748161,
      -2.0110478280374986,
      -1.9660510198599461,
      -1.9210843029489415,
      -1.8761476773044847,
      -1.831241142926576,
      -1.7863646998152152,
      -1.741518347970395,
      -1.696702087392139,
      -1.6519159180804128,
      -1.607159840035256,
      -1.5624338532566255,
      -1.517737957744561,
      -1.4730721534990194,
      -1.4284364405200543,
      -1.3838308188076154,
      -1.3392552883617461,
      -1.2947098491824032,
      -1.2501945012696296,
      -1.2057092446233824,
      -1.1612540792436938,
      -1.116829005130546,
      -1.0724340222839606,
      -1.0280691307039085,
      -0.9837343303904224,
      -0.9394296213434661,
      -0.8951550035630651,
      -0.8509104770492046,
      -0.8066960418019101,
      -0.7625116978211419,
      -0.7183574451069432,
      -0.6742332836592744,
      -0.6301392134781714,
      -0.5860752345635912,
      -0.5420413469155841,
      -0.49803755053410687,
      -0.45406384541919553,
      -0.4101202315708232,
      -0.36620670898899854,
      -0.32232327767371494,
      -0.27846993762498606,
      -0.2346466888428089,
      -0.19085353132717583,
      -0.14709046507809093,
      -0.10335749009555723,
      -0.0596546063795681,
      -0.015981813930119545,
      0.02766088725277378,
      0.07127349716911588,
      0.11485601581890985,
      0.1584084432021597,
      0.20193077931885786,
      0.245423024169019,
      0.2888851777526214,
      0.3323172400696796,
      0.3757192111201862,
      0.4190910909041451,
      0.46243287942155586,
      0.5057445766724225,
      0.5490261826567445,
      0.5922776973745028,
      0.635499120825731,
      0.6786904530103934,
      0.7218516939285259,
      0.7649828435800925,
      0.8080839019651398,
      0.8511548690836106,
      0.8941957449355514,
      0.9372065295209264,
      0.9801872228397679,
      1.023137824892047,
      1.0660583356778035,
      1.1089487551969868,
      1.1518090834496404,
      1.1946393204357244,
      1.237439466155282,
      1.2802095206082738,
      1.3229494837947322,
      1.3656593557146353,
      1.4083391363680013,
      1.4509888257547978,
      1.4936084238750647,
      1.536197930728769,
      1.57875734631594,
      1.6212866706365556,
      1.6637859036906306,
      1.7062550454781436,
      1.7486940959991228,
      1.791103055253536,
      1.8334819232414106
    ],
    "eps_imag": [
      6.265688052337806,
      6.330199499058065,
      6.395040092237563,
      6.460209831876301,
      6.525708717974276,
      6.591536750531493,
      6.657693929547947,
      6.724180255023639,
      6.790995726958571,
      6.8581403453527425,
      6.925907560030759,
      7.0010832285075715,
      7.076658257960923,
      7.152632648390816,
      7.229006399797249,
      7.305779512180223,
      7.382951985539736,
      7.46052381987579,
      7.538495015188385,
      7.61686557147752,
      7.695635488743196,
      7.774804766985412,
      7.854373406204169,
      7.934341406399465,
      8.014708767571303,
      8.09547548971968,
      8.1766415728446,
      8.25820701694606,
      8.340171822024057,
      8.422535988078598,
      8.505299515109675,
      8.595820427561751,
      8.69905207340246,
      8.80275289598407,
      8.906922895306595,
      9.011562071370024,
      9.116670424174362,
      9.222247953719608,
      9.32829466000576,
      9.434810543032823,
      9.541795602800791,
      9.649249839309668,
      9.757173252559452,
      9.865565842550145,
      9.97442760928174,
      10.083758552754247,
      10.193558672967663,
      10.303827969921988,
      10.41456644361722,
      10.525774094053359,
      10.637450921230405,
      10.749596925148362,
      10.862212105807224,
      10.975296463206993,
      11.088849997347673,
      11.169142871036987,
      11.238868574630477,
      11.308692396601009,
      11.378614336948585,
      11.448634395673205,
      11.518752572774869,
      11.588968868253577,
      11.659283282109325,
      11.729695814342119,
      11.800206464951959,
      11.87081523393884,
      11.941522121302762,
      12.012327127043731,
      12.083230251161744,
      12.1542314936568,
      12.225330854528897,
      12.296528333778042,
      12.367823931404228,
      12.439217647407459,
      12.510709481787734,
      12.582299434545048,
      12.653987505679408,
      12.725773695190815,
      12.797658003079263,
      12.869640429344752,
      12.941720973987287,
      13.013899637006867,
      13.06258317537686,
      13.088641489837652,
      13.114724645223387,
      13.140832641534054,
      13.166965478769658,
      13.193123156930202,
      13.219305676015681,
      13.245513036026098,
      13.271745236961452,
      13.298002278821743,
      13.32428416160697,
      13.350590885317136,
      13.376922449952238,
      13.403278855512276,
      13.429660101997253,
      13.456066189407165,
      13.482497117742016,
      13.508952887001803,
      13.535433497186524,
      13.561938948296188,
      13.588469240330785,
      13.61502437329032,
      13.641604347174793,
      13.668209161984203,
      13.694838817718548,
      13.72149331437783,
      13.74817265196205,
      13.774876830471207,
      13.8016058499053,
      13.828359710264333,
      13.855138411548301,
      13.881941953757206,
      13.928701012684286,
      13.98334175947049,
      14.038085914462929,
      14.092933477661608,
      14.147884449066522,
      14.202938828677675,
      14.258096616495065,
      14.313357812518692,
      14.368722416748556,
      14.424190429184657,
      14.479761849826994,
      14.53543667867557,
      14.591214915730383,
      14.64709656099143,
      14.70308161445872,
      14.759170076132243,
      14.815361946012004,
      14.871657224098003,
      14.928055910390237,
      14.984558004888711,
      15.04116350759342,
      15.097872418504368,
      15.154684737621553,
      15.211600464944976,
      15.268619600474633,
      15.325742144210528,
      15.382968096152663,
      15.44029745630103,
      15.497730224655639,
      15.555266401216482,
      15.612905985983565,
      15.670648978956882,
      15.728495380136442,
      15.786445189522233,
      15.84449840711426,
      15.902655032912532,
      15.960915066917035,
      16.022088550800436,
      16.09959005521844,
      16.177278392829628,
      16.255153563634003,
      16.33321556763156,
      16.411464404822308,
      16.489900075206243,
      16.568522578783362,
      16.647331915553664,
      16.726328085517157,
      16.805511088673835,
      16.8848809250237,
      16.964437594566753,
      17.044181097302985,
      17.12411143323241,
      17.204228602355027,
      17.284532604670822,
      17.365023440179804,
      17.445701108881966,
      17.52656561077732,
      17.60761694586586,
      17.68885511414759,
      17.770280115622505,
      17.85189195029061,
      17.933690618151893,
      18.01567611920637,
      18.097848453454027,
      18.180207620894873,
      18.26275362152891,
      18.345486455356124,
      18.428406122376526,
      18.511512622590118,
      18.594805955996897,
      18.67828612259686,
      18.761953122390008,
      18.845806955376347,
      18.929847621555872,
      19.01407512092858,
      19.098489453494473,
      19.183090619253555,
      19.267878618205824,
      19.35285345035128,
      19.438015115689918,
      19.523363614221743,
      19.60889894594676,
      19.696395132494356,
      19.8105112191316,
      19.924904477707738,
      20.039574908222757,
      20.154522510676664,
      20.269747285069453,
      20.385249231401122,
      20.501028349671685,
      20.617084639881128,
      20.73341810202946,
      20.850028736116677,
      20.966916542142773,
      21.08408152010776,
      21.20152367001163,
      21.319242991854384,
      21.437239485636027,
      21.55551315135655,
      21.67406398901596,
      21.792891998614255,
      21.911997180151438,
      22.031379533627504,
      22.151039059042454,
      22.27097575639629,
      22.391189625689012,
      22.51168066692062,
      22.63244888009111,
      22.753494265200484,
      22.874816822248746,
      22.996416551235896,
      23.11829345216193,
      23.240447525026845,
      23.362878769830644,
      23.48558718657333,
      23.608572775254906,
      23.73183553587536,
      23.85537546843471,
      23.979192572932927,
      24.10328684937004,
      24.22765829774604,
      24.352306918060926,
      24.477232710314695,
      24.602435674507344,
      24.727915810638883,
      24.853673118709306,
      24.979707598718615,
      25.10601925066681,
      25.232608074553887,
      25.35947407037985,
      25.486617238144703,
      25.614037577848435,
      25.74173508949106,
      25.869709773072557,
      25.997961628592947,
      26.126490656052223,
      26.255296855450386,
      26.38438022678743,
      26.48818730857989,
      26.59104607325028,
      26.69404622087927,
      26.79718775146685,
      26.900470665013035,
      27.003894961517812,
      27.107460640981188,
      27.21116770340316,
      27.315016148783734,
      27.419005977122897,
      27.52313718842066,
      27.627409782677006,
      27.73182375989196,
      27.836379120065516,
      27.941075863197664,
      28.045913989288415,
      28.15089349833776,
      28.256014390345698,
      28.361276665312236,
      28.466680323237373,
      28.5722253641211,
      28.67791178796343,
      28.78373959476436,
      28.889708784523872,
      28.995819357241995,
      29.102071312918714,
      29.208464651554024,
      29.314999373147934,
      29.421675477700443,
      29.528492965211544,
      29.63545183568125,
      29.742552089109545,
      29.849793725496433,
      29.957176744841927,
      30.064701147146014,
      30.172366932408696,
      30.28017410062998,
      30.388122651809862,
      30.49621258594834,
      30.604443903045407,
      30.71281660310108,
      30.82133068611535,
      30.929986152088205,
      31.038783001019667,
      31.147721232909728,
      31.256800847758377,
      31.366021845565626,
      31.475384226331478,
      31.58488799005592,
      31.694533136738958,
      31.8043196663806,
      31.91424757898083,
      32.024316874539664,
      32.1345275530571,
      32.24487961453312,
      32.35537305896774,
      32.46600788636096,
      32.57678409671277,
      32.68770169002319,
      32.7987606662922,
      32.909961025519806,
      33.02130276770601,
      33.13278589285081,
      33.2444104009542,
      33.3561762920162,
      33.468083566036796,
      33.58013222301598,
      33.692322262953766,
      33.801666005315056,
      33.87621621485254,
      33.95071530435157,
      34.025163273812154,
      34.099560123234276,
      34.17390585261796,
      34.24820046196319,
      34.32244395126997,
      34.39663632053829,
      34.47077756976816,
      34.54486769895959,
      34.61890670811256,
      34.69289459722708,
      34.76683136630315,
      34.840717015340765,
      34.914551544339936,
      34.98833495330065,
      35.062067242222916,
      35.135748411106725,
      35.20937845995209,
      35.282957388759,
      35.35648519752746,
      35.429961886257466,
      35.50338745494903,
      35.57676190360213,
      35.65008523221679,
      35.723357440792995,
      35.796578529330745,
      35.869748497830045,
      35.942867346290896,
      36.0159350747133,
      36.08895168309724,
      36.16191717144274,
      36.23483153974978,
      36.307694788018374,
      36.38050691624852,
      36.45326792444021,
      36.52597781259345,
      36.59863658070824,
      36.67124422878457,
      36.743800756822466,
      36.8163061648219,
      36.88876045278288,
      36.96116362070541,
      37.033515668589494,
      37.10581659643513,
      37.17806640424231,
      37.250265092011034,
      37.32241265974131,
      37.39450910743314,
      37.466554435086515,
      37.53854864270144,
      37.61049173027791,
      37.68238369781593,
      37.754224545315495,
      37.82601427277662,
      37.897752880199285,
      37.9694403675835,
      38.04107673492926,
      38.112661982236574,
      38.18419610950544,
      38.255679116735855,
      38.32711100392781,
      38.39849177108132,
      38.46982141819638,
      38.54109994527299,
      38.61232735231114,
      38.68350363931085,
      38.75462880627209,
      38.8257028531949,
      38.896725780079244,
      38.96769758692514,
      39.03861827373258,
      39.109487840501586,
      39.180306287232135,
      39.25107361392422,
      39.32178982057787,
      39.392454907193056,
      39.4630688737698,
      39.533631720308094,
      39.60414344680793,
      39.67460405326931,
      39.745013539692245,
      39.81537190607674,
      39.88567915242277,
      39.955935278730344,
      40.026140284999485,
      40.096294171230156,
      40.16639693742239,
      40.212822044161015,
      40.23734372692553,
      40.26187268857314,
      40.286408929103835,
      40.31095244851761,
      40.33550324681448,
      40.360061323994444,
      40.38462668005748,
      40.40919931500362,
      40.43377922883284,
      40.458366421545136,
      40.48296089314053,
      40.507562643618996,
      40.53217167298057,
      40.55678798122522,
      40.58141156835296,
      40.606042434363786,
      40.6306805792577,
      40.655326003034695,
      40.67997870569478,
      40.70463868723796,
      40.72930594766421,
      40.75398048697357,
      40.778662305165994,
      40.80335140224152,
      40.82804777820013,
      40.85275143304182,
      40.8774623667666,
      40.90218057937447,
      40.92690607086543,
      40.95163884123947,
      40.976378890496605,
      41.00112621863681,
      41.02588082566012,
      41.0506427115665,
      41.07541187635598,
      41.10018832002856,
      41.124972042584204,
      41.14976304402294,
      41.174561324344765,
      41.19936688354967,
      41.224179721637675,
      41.24899983860876,
      41.273827234462935,
      41.2986619092002,
      41.32350386282054,
      41.34835309532397,
      41.373209606710496,
      41.398073396980095,
      41.42294446613279,
      41.447822814168575,
      41.47270844108745,
      41.497601346889404,
      41.52250153157445,
      41.54740899514257,
      41.572323737593784,
      41.59724575892808,
      41.622175059145476,
      41.64711163824596,
      41.67205549622952,
      41.69700663309617,
      41.72196504884591,
      41.74693074347873,
      41.77190371699464,
      41.79688396939364,
      41.82187150067573,
      41.8468663108409,
      41.87186839988916,
      41.896877767820506,
      41.92189441463494,
      41.94691834033245,
      41.97194954491306,
      41.99698802837676,
      42.02203379072354,
      42.04708683195341,
      42.072147152066364,
      42.0972147510624,
      42.12228962894153,
      42.14737178570374,
      42.172461221349046,
      42.19755793587744,
      42.22266192928891,
      42.24777320158348,
      42.272891752761126,
      42.29801758282186,
      42.32315069176568,
      42.3482910795926,
      42.3734387463026,
      42.398593691895684,
      42.42375591637185,
      42.44892541973111,
      42.47410220197346,
      42.49928626309888,
      42.52447760310741,
      42.54967622199902,
      42.57488211977371,
      42.60009529643149,
      42.62531575197236,
      42.65054348639631,
      42.67577849970335,
      42.70102079189347,
      42.726270362966694,
      42.751527212923,
      42.77679134176238,
      42.80206274948486,
      42.827341436090414,
      42.85262740157907,
      42.8779206459508,
      42.90322116920562,
      42.92852897134353,
      42.953844052364545,
      42.97916641226862,
      43.004496051055796,
      43.029832968726055,
      43.05517716527939,
      43.080528640715826,
      43.10588739503534,
      43.131253428237954,
      43.17548242489019,
      43.24383465403703,
      43.31222222696782,
      43.38064514368254,
      43.44910340418123,
      43.51759700846386,
      43.58612595653044,
      43.65469024838095,
      43.72328988401542,
      43.791924863433835,
      43.860595186636196,
      43.929300853622514,
      43.998041864392775,
      44.06681821894697,
      44.13562991728513,
      44.20447695940722,
      44.27335934531327,
      44.34227707500326,
      44.41123014847721,
      44.48021856573509,
      44.54924232677693,
      44.6183014316027,
      44.687395880212435,
      44.75652567260611,
      44.82569080878373,
      44.894891288745306,
      44.96412711249083,
      45.033398280020286,
      45.1027047913337,
      45.172046646431056,
      45.24142384531236,
      45.31083638797762,
      45.38028427442681,
      45.44976750465997,
      45.519286078677055,
      45.5888399964781,
      45.65842925806308,
      45.728053863432024,
      45.79771381258491,
      45.867409105521745,
      45.937139742242515,
      46.00690572274724,
      46.07670704703591,
      46.14654371510853,
      46.21641572696509,
      46.28632308260561,
      46.35626578203007,
      46.42624382523848,
      46.49625721223083,
      46.56630594300713,
      46.63639001756738,
      46.706509435911585,
      46.776664198039725,
      46.846854303951815,
      46.91707975364785,
      46.987340547127836,
      47.05763668439176,
      47.12796816543964,
      47.19833499027147,
      47.26873715888725,
      47.33917467128696,
      47.40964752747063,
      47.480155727438245,
      47.5506992711898,
      47.62127815872532,
      47.69189239004477,
      47.76254196514817,
      47.83322688403552,
      47.90394714670682,
      47.974702753162056,
      48.045493703401256,
      48.1163199974244,
      48.18718163523148,
      48.25807861682251,
      48.32901094219749,
      48.39997861135642,
      48.47098162429929,
      48.54201998102612,
      48.61309368153689,
      48.684202725831604,
      48.75534711391027,
      48.826526845772875,
      48.89774192141943,
      48.96899234084993,
      49.0402781040644,
      49.11159921106279,
      49.182955661845135,
      49.25434745641142,
      49.32577459476167,
      49.39723707689585,
      49.468734902813985,
      49.54026807251607,
      49.6118365860021,
      49.683440443272076,
      49.755079644325996,
      49.826754189163864,
      49.898464077785675,
      49.97020931019144,
      50.04198988638116,
      50.11380580635482,
      50.18565707011242,
      50.25754367765398,
      50.32946562897947,
      50.40142292408892,
      50.47341556298232,
      50.545443545659666,
      50.61750687212095,
      50.68960554236619,
      50.76173955639536,
      50.8339089142085,
      50.906113615805566,
      50.97835366118659,
      51.05062905035156,
      51.122939783300474,
      51.195285860033344,
      51.267667280550164,
      51.340084044850926,
      51.41253615293563,
      51.48502360480428,
      51.55754640045688,
      51.63010453989343,
      51.70269802311393,
      51.775326850118375,
      51.84799102090676,
      51.9206905354791,
      51.99342539383538,
      52.066195595975614,
      52.13900114189979,
      52.211842031607915,
      52.2847182651,
      52.357629842376014,
      52.43057676343598,
      52.503559028279895,
      52.57657663690775,
      52.649629589319574,
      52.72271788551532,
      52.79584152549503,
      52.869000509258676,
      52.94219483680627,
      53.01542450813781,
      53.0886895232533,
      53.16198988215274,
      53.23532558483613,
      53.30869663130346,
      53.38210302155474,
      53.45554475558997,
      53.52902183340914,
      53.602534255012266,
      53.676082020399335,
      53.74966512957035,
      53.82328358252531,
      53.89693737926422,
      53.970626519787075,
      54.04435100409388,
      54.11811083218463,
      54.19190600405934,
      54.26573651971798,
      54.339602379160574,
      54.413503582387115,
      54.487440129397605,
      54.56141202019203,
      54.635419254770426,
      54.70946183313275,
      54.78353975527903,
      54.857653021209245,
      54.91793749107674,
      54.88206552007672,
      54.84618791848743,
      54.81030468630886,
      54.774415823541005,
      54.73852133018387,
      54.70262120623747,
      54.66671545170179,
      54.630804066576815,
      54.59488705086259,
      54.55896440455906,
      54.52303612766627,
      54.4871022201842,
      54.451162682112844,
      54.415217513452205,
      54.37926671420231,
      54.34331028436312,
      54.30734822393467,
      54.271380532916915,
      54.235407211309905,
      54.199428259113596,
      54.16344367632803,
      54.12745346295317,
      54.09145761898905,
      54.05545614443563,
      54.01944903929296,
      53.98343630356098,
      53.947417937239734,
      53.91139394032922,
      53.87536431282942,
      53.83932905474035,
      53.803288166061996,
      53.76724164679435,
      53.731189496937446,
      53.69513171649126,
      53.6590683054558,
      53.622999263831055,
      53.586924591617034,
      53.55084428881374,
      53.51475835542116,
      53.4786667914393,
      53.44256959686817,
      53.40646677170776,
      53.37035831595807,
      53.33424422961911,
      53.298124512690855,
      53.261999165173336,
      53.22586818706654,
      53.18973157837046,
      53.15358933908511,
      53.117441469210476,
      53.081287968746565,
      53.04512883769337,
      53.0089640760509,
      52.97279368381916,
      52.93661766099814,
      52.90043600758783,
      52.86424872358826,
      52.82805580899939,
      52.791857263821264,
      52.75565308805385,
      52.71944328169717,
      52.68322784475119,
      52.64700677721595,
      52.61078007909142,
      52.57454775037762,
      52.53830979107453,
      52.50206620118219,
      52.465816980700545,
      52.42956212962964,
      52.39330164796944,
      52.35703553571997,
      52.320763792881216,
      52.2844864194532,
      52.248203415435896,
      52.211914780829325,
      52.175620515633454,
      52.139320619848334,
      52.1030150934739,
      52.06670393651021,
      52.03038714895724,
      51.99406473081499,
      51.95773668208347,
      51.921403002762666,
      51.885063692852576,
      51.84871875235322,
      51.81236818126458,
      51.77601197958667,
      51.73965014731947,
      51.703282684463005,
      51.66690959101725,
      51.63053086698223,
      51.59414651235792,
      51.55775652714434,
      51.52136091134148,
      51.48495966494934,
      51.44855278796793,
      51.412140280397225,
      51.37572214223726,
      51.339298373488006,
      51.30286897414948,
      51.266433944221674,
      51.229993283704594,
      51.19354699259822,
      51.157095070902585,
      51.12063751861767,
      51.08417433574348,
      51.047705522280005,
      51.01123107822725
    ]
  }
}